pynnacle_uno/__init__.py
pynnacle_uno/main.py
pynnacle_uno-1.0.0.dist-info/LICENSE
pynnacle_uno-1.0.0.dist-info/METADATA
pynnacle_uno-1.0.0.dist-info/WHEEL
pynnacle_uno-1.0.0.dist-info/top_level.txt
pynnacle_uno-1.0.0.dist-info/RECORD
