Metadata-Version: 2.1
Name: pynnacle_uno
Version: 1.0.0
Summary: A Python module that provides hands-on robotics coding experience in Python that closely mirrors the structure and functionality of Arduino's programming language.
Home-page: https://github.com/Red-Pula/Pynnacle-Uno
Author: Rafael Red Angelo M. Hizon, Jenel M. Justo, Serena Mae C.S. Lee
Author-email: redhizon@gmail.com, jenel.just88@gmail.com, nmae.lee@gmail.com
License: GNU Affero General Public License
Classifier: License :: OSI Approved :: GNU Affero General Public License v3
Classifier: Operating System :: Microsoft :: Windows
Classifier: Programming Language :: Python :: 3.7
Classifier: Programming Language :: Python :: 3.8
Classifier: Programming Language :: Python :: 3.9
Classifier: Programming Language :: Python :: 3.10
Classifier: Programming Language :: Python :: 3.11
Classifier: Programming Language :: Python :: 3.12
Classifier: Programming Language :: Python :: 3.13
License-File: LICENSE
Requires-Dist: pymata4 >=1.15
